pdivas/__init__.py
pdivas/__main__.py
pdivas/scoring_to_vcf.py
pdivas/vcf2tsv.py
pdivas/model/PDIVAS.sav
pdivas-1.2.0.dist-info/LICENSE
pdivas-1.2.0.dist-info/METADATA
pdivas-1.2.0.dist-info/WHEEL
pdivas-1.2.0.dist-info/entry_points.txt
pdivas-1.2.0.dist-info/top_level.txt
pdivas-1.2.0.dist-info/RECORD
