Metadata-Version: 2.1
Name: pdivas
Version: 1.2.0
Summary: PDIVAS: Pathogenicity predictor of Deep-Intronic Variants causing Aberrant Splicing
Home-page: https://github.com/shiro-kur/PDIVAS
Author: Ryo Kurosawa
Author-email: a0160561@yahoo.co.jp
License: MIT
License-File: LICENSE
Requires-Dist: pandas
Requires-Dist: numpy
Requires-Dist: cyvcf2
Requires-Dist: scikit-learn==1.0.2
